ppca_rs-0.5.1.dist-info/METADATA
ppca_rs-0.5.1.dist-info/WHEEL
ppca_rs/py.typed
ppca_rs/__init__.py
ppca_rs/ppca_rs.pyi
ppca_rs/ppca_rs.cpython-311-x86_64-linux-gnu.so
ppca_rs-0.5.1.dist-info/RECORD
