Metadata-Version: 2.1
Name: ppca-rs
Version: 0.5.1
Classifier: Programming Language :: Rust
Classifier: License :: OSI Approved :: MIT License
Classifier: Topic :: Scientific/Engineering :: Artificial Intelligence
Classifier: Programming Language :: Python :: Implementation :: CPython
Classifier: Programming Language :: Python :: Implementation :: PyPy
Requires-Dist: cffi
Requires-Dist: numpy
Summary: Python+Rust implementation of the Probabilistic Principal Component Analysis model
Author-email: Pedro B. Arruda <parruda@findhotel.net>
Requires-Python: >=3.7
Project-URL: Homepage, https://github.com/FindHotel/ppca_rs
